ppge/__init__.py
ppge/geomet/__init__.py
ppge/geomet/esri.py
ppge/geomet/geopackage.py
ppge/geomet/tool.py
ppge/geomet/util.py
ppge/geomet/wkb.py
ppge/geomet/wkt.py
ppge/pyshp/__init__.py
ppge/pyshp/setup.py
pure_python_geospatial_export-0.1.2.dist-info/METADATA
pure_python_geospatial_export-0.1.2.dist-info/WHEEL
pure_python_geospatial_export-0.1.2.dist-info/top_level.txt
pure_python_geospatial_export-0.1.2.dist-info/RECORD
