Metadata-Version: 2.4
Name: Pure-Python-Geospatial-Export
Version: 0.1.2
Provides-Extra: test
Requires-Dist: click==8.2.1; extra == "test"
Requires-Dist: geopandas==1.0.1; extra == "test"
Requires-Dist: py==1.11.0; extra == "test"
Requires-Dist: pytest>=3.7; extra == "test"
Requires-Dist: ruff==0.12.2; extra == "test"
Requires-Dist: shapely==2.0.7; extra == "test"
